{
  "fitness" : 0.95705426,
  "nodes" : [ {
    "id" : 8,
    "type" : "Treasure",
    "difficulty" : 0.0,
    "reward" : 0.73134094
  }, {
    "id" : 10,
    "type" : "Treasure",
    "difficulty" : 0.0,
    "reward" : 0.9656368
  }, {
    "id" : 11,
    "type" : "EnemyAndTreasure",
    "difficulty" : 0.93065315,
    "reward" : 0.70565486
  }, {
    "id" : 6,
    "type" : "Empty",
    "difficulty" : 0.0,
    "reward" : 0.0
  }, {
    "id" : 12,
    "type" : "Empty",
    "difficulty" : 0.0,
    "reward" : 0.0
  }, {
    "id" : 5,
    "type" : "Enemies",
    "difficulty" : 0.964304,
    "reward" : 0.0
  }, {
    "id" : 16,
    "type" : "Enemies",
    "difficulty" : 0.95080197,
    "reward" : 0.0
  }, {
    "id" : 17,
    "type" : "Empty",
    "difficulty" : 0.0,
    "reward" : 0.0
  }, {
    "id" : 13,
    "type" : "EnemyAndTreasure",
    "difficulty" : 0.21763837,
    "reward" : 0.016226858
  }, {
    "id" : 2,
    "type" : "Empty",
    "difficulty" : 0.0,
    "reward" : 0.0
  }, {
    "id" : 4,
    "type" : "Enemies",
    "difficulty" : 0.3705904,
    "reward" : 0.0
  }, {
    "id" : 1,
    "type" : "EnemyAndTreasure",
    "difficulty" : 0.42910725,
    "reward" : 0.9520804
  }, {
    "id" : 7,
    "type" : "Treasure",
    "difficulty" : 0.0,
    "reward" : 0.2589254
  }, {
    "id" : 3,
    "type" : "EnemyAndTreasure",
    "difficulty" : 0.08284182,
    "reward" : 0.1027247
  }, {
    "id" : 15,
    "type" : "Treasure",
    "difficulty" : 0.0,
    "reward" : 0.016022438
  }, {
    "id" : 9,
    "type" : "Enemies",
    "difficulty" : 0.11600648,
    "reward" : 0.0
  }, {
    "id" : 18,
    "type" : "Enemies",
    "difficulty" : 0.6962823,
    "reward" : 0.0
  }, {
    "id" : 14,
    "type" : "Treasure",
    "difficulty" : 0.0,
    "reward" : 0.1280075
  }, {
    "id" : 19,
    "type" : "Start",
    "difficulty" : 0.0,
    "reward" : 0.0
  }, {
    "id" : 20,
    "type" : "Exit",
    "difficulty" : 0.0,
    "reward" : 0.0
  }, {
    "id" : 0,
    "type" : "Empty",
    "difficulty" : 0.0,
    "reward" : 0.0
  } ],
  "edges" : [ {
    "from" : 8,
    "to" : 12
  }, {
    "from" : 8,
    "to" : 13
  }, {
    "from" : 10,
    "to" : 14
  }, {
    "from" : 10,
    "to" : 15
  }, {
    "from" : 11,
    "to" : 16
  }, {
    "from" : 6,
    "to" : 11
  }, {
    "from" : 12,
    "to" : 17
  }, {
    "from" : 5,
    "to" : 9
  }, {
    "from" : 5,
    "to" : 10
  }, {
    "from" : 16,
    "to" : 19
  }, {
    "from" : 17,
    "to" : 20
  }, {
    "from" : 13,
    "to" : 18
  }, {
    "from" : 2,
    "to" : 6
  }, {
    "from" : 2,
    "to" : 7
  }, {
    "from" : 1,
    "to" : 4
  }, {
    "from" : 1,
    "to" : 5
  }, {
    "from" : 3,
    "to" : 8
  }, {
    "from" : 0,
    "to" : 1
  }, {
    "from" : 0,
    "to" : 2
  }, {
    "from" : 0,
    "to" : 3
  } ]
}